toronto_open_data/__init__.py
toronto_open_data/api.py
toronto_open_data/cache.py
toronto_open_data/config.py
toronto_open_data/core.py
toronto_open_data/loaders.py
toronto_open_data-0.2.1.dist-info/METADATA
toronto_open_data-0.2.1.dist-info/WHEEL
toronto_open_data-0.2.1.dist-info/licenses/LICENSE
toronto_open_data-0.2.1.dist-info/RECORD
