Metadata-Version: 2.4
Name: toronto-open-data
Version: 0.2.1
Summary: A Python package for accessing Toronto Open Data Portal
Project-URL: Homepage, https://github.com/alexwolson/toronto-open-data
Project-URL: Repository, https://github.com/alexwolson/toronto-open-data.git
Project-URL: Issues, https://github.com/alexwolson/toronto-open-data/issues
Project-URL: Changelog, https://github.com/alexwolson/toronto-open-data/blob/main/CHANGELOG.md
Author-email: Alex Olson <alexwaolson@gmail.com>
License-File: LICENSE
Classifier: Development Status :: 4 - Beta
Classifier: Intended Audience :: Developers
Classifier: Intended Audience :: Science/Research
Classifier: License :: OSI Approved :: MIT License
Classifier: Operating System :: OS Independent
Classifier: Programming Language :: Python :: 3
Classifier: Programming Language :: Python :: 3.8
Classifier: Programming Language :: Python :: 3.9
Classifier: Programming Language :: Python :: 3.10
Classifier: Programming Language :: Python :: 3.11
Classifier: Programming Language :: Python :: 3.12
Classifier: Topic :: Database
Classifier: Topic :: Scientific/Engineering :: Information Analysis
Classifier: Topic :: Software Development :: Libraries :: Python Modules
Requires-Python: >=3.8
Requires-Dist: ckanapi>=0.0.0
Requires-Dist: pandas>=1.3.0
Requires-Dist: requests>=2.25.0
Requires-Dist: tqdm>=4.60.0
Provides-Extra: dev
Requires-Dist: bandit>=1.7.0; extra == 'dev'
Requires-Dist: black>=23.0.0; extra == 'dev'
Requires-Dist: flake8>=6.0.0; extra == 'dev'
Requires-Dist: isort>=5.12.0; extra == 'dev'
Requires-Dist: mypy>=1.0.0; extra == 'dev'
Requires-Dist: pre-commit>=3.0.0; extra == 'dev'
Requires-Dist: pytest-cov>=4.0.0; extra == 'dev'
Requires-Dist: pytest-mock>=3.10.0; extra == 'dev'
Requires-Dist: pytest>=7.0.0; extra == 'dev'
Requires-Dist: safety>=2.0.0; extra == 'dev'
Provides-Extra: docs
Requires-Dist: myst-parser>=1.0.0; extra == 'docs'
Requires-Dist: sphinx-rtd-theme>=1.2.0; extra == 'docs'
Requires-Dist: sphinx>=6.0.0; extra == 'docs'
Provides-Extra: test
Requires-Dist: pytest-cov>=4.0.0; extra == 'test'
Requires-Dist: pytest-mock>=3.10.0; extra == 'test'
Requires-Dist: pytest>=7.0.0; extra == 'test'
